simple_cli_args/__init__.py
simple_cli_args/cli_args.py
simple_cli_args-1.0.dist-info/LICENSE
simple_cli_args-1.0.dist-info/METADATA
simple_cli_args-1.0.dist-info/WHEEL
simple_cli_args-1.0.dist-info/top_level.txt
simple_cli_args-1.0.dist-info/RECORD
