Metadata-Version: 2.1
Name: simple-cli-args
Version: 1.0
Summary: An enhancement of argparse package for its simplest usages
Home-page: https://github.com/zellerede/simple-cli-args
Author: Bertalan Pecsi
Author-email: zellerede@gmail.com
License: UNKNOWN
Keywords: argparse cli cli-args cli_args simple-cli-args simple_cli_args
Platform: UNKNOWN
Classifier: Programming Language :: Python :: 3
Classifier: License :: OSI Approved :: MIT License
Classifier: Operating System :: OS Independent
Requires-Dist: termcolor
